flare/__init__.py
flare_discord.py-1.0.0.dist-info/LICENSE
flare_discord.py-1.0.0.dist-info/METADATA
flare_discord.py-1.0.0.dist-info/WHEEL
flare_discord.py-1.0.0.dist-info/top_level.txt
flare_discord.py-1.0.0.dist-info/RECORD
