Metadata-Version: 2.1
Name: flare-discord.py
Version: 1.0.0
Summary: Provides a simple, single import cog to add a checkable page to your bot for uptime status monitoring
Home-page: http://github.com/JakeCover/Flare
Author: Cobular
Author-email: python@cobular.com
License: MIT
Keywords: Discord,Discord.py,Uptime,Monitoring,Flare,Discord Uptime Monitoring,UptimeRobot
Platform: UNKNOWN
Classifier: License :: OSI Approved :: MIT License
Classifier: Intended Audience :: Developers
Classifier: Natural Language :: English
Classifier: Operating System :: OS Independent
Classifier: Programming Language :: Python :: 3.6
Classifier: Programming Language :: Python :: 3.7
Classifier: Programming Language :: Python :: 3.8
Classifier: Programming Language :: Python :: 3.9
Classifier: Topic :: System :: Monitoring
Classifier: Topic :: Software Development :: Libraries :: Python Modules
Classifier: Topic :: Utilities
Requires-Dist: discord.py (<1.7.0,>=1.5.0)
